django_asana-1.3.4.dist-info/DESCRIPTION.rst
django_asana-1.3.4.dist-info/METADATA
django_asana-1.3.4.dist-info/RECORD
django_asana-1.3.4.dist-info/WHEEL
django_asana-1.3.4.dist-info/metadata.json
django_asana-1.3.4.dist-info/top_level.txt
djasana/__init__.py
djasana/admin.py
djasana/apps.py
djasana/connect.py
djasana/models.py
djasana/settings.py
djasana/urls.py
djasana/utils.py
djasana/views.py
djasana/management/__init__.py
djasana/management/utils.py
djasana/management/commands/__init__.py
djasana/management/commands/sync_from_asana.py
djasana/migrations/0001_squashed_0001_initial.py
djasana/migrations/0001_squashed_0015_adds_task_start_on.py
djasana/migrations/0002_adds_project_start_on.py
djasana/migrations/0002_alter_name_max_len_etc.py
djasana/migrations/0003_adds_story_is_edited_is_pinned.py
djasana/migrations/0003_project_allows_blank.py
djasana/migrations/0004_adds_attachment_type.py
djasana/migrations/0004_adds_synctoken.py
djasana/migrations/0005_adds_custom_field_settings_rich_text_project_status.py
djasana/migrations/0005_adds_webhook.py
djasana/migrations/0006_adds_custom_fields.py
djasana/migrations/0006_adds_defaults.py
djasana/migrations/0007_adds_gid.py
djasana/migrations/0007_alter_task_completed.py
djasana/migrations/0008_add_resource_type_subtype.py
djasana/migrations/0008_adds_task_blank_null.py
djasana/migrations/0009_adds_tag_fields.py
djasana/migrations/0009_default_ordering.py
djasana/migrations/0010_expands_resource_subtype.py
djasana/migrations/0010_short_webhook_secret.py
djasana/migrations/0011_modifies_choices.py
djasana/migrations/0012_project_team_allows_null.py
djasana/migrations/0013_adds_on_delete.py
djasana/migrations/0014_user_email_allows_null.py
djasana/migrations/0015_adds_task_start_on.py
djasana/migrations/__init__.py
djasana/tests/__init__.py
djasana/tests/fixtures.py
djasana/tests/test_connect.py
djasana/tests/test_models.py
djasana/tests/test_sync_from_asana.py
djasana/tests/test_views.py
